[
    {
        "id": 1,
        "type": 2,
        "title": "MIS FOTOGRAFÍAS",
        "content": {
            "text": "Saco algunas fotografías <br><strong>¿Validamos si te gustaría verlas?</strong>",
            "buttontext": {
                "one": "Validemos"
            },
            "optionone": {
                "buttonimages": true
            }
        },
        "image": "instagram",
        "url": "https://instagram.com/deibyod/"
    },
    {
        "id": 2,
        "type": 3,
        "title": "MIS IDEAS EN CORTO",
        "content": {
            "text": "Si eres de los que prefieren intercambiar “buenas” ideas en corto, te invito a seguirnos."
        },
        "image": "twitter",
        "url": "https://twitter.com/deibyod"
    },
    {
        "id": 3,
        "type": 1,
        "title": "MI CIRCULO DE AMIG@S",
        "content": {
            "text": "¿Nos conocemos personalmente? Me alegraría conectar contigo más cotidianamente. Continuemos conociéndonos y conectando."
        },
        "image": "facebook",
        "url": "https://www.facebook.com/deibyod/"
    },
    {
        "id": 4,
        "type": 2,
        "title": "MIS VIAJES",
        "content": {
            "text": "Ocasionalmente experimento con algo. Conoce nuestro naciente canal de viajes GoTravel."
        },
        "image": "youtube",
        "url": "https://www.youtube.com/channel/UC7PSm60sA0_URrmLZ9L_q3Q"
    },
    {
        "id": 5,
        "type": 3,
        "title": "MIS VIDEOS DIVERSOS",
        "content": {
            "text": "Algunos videos muy antiguos y diversos en mi viejo canal."
        },
        "image": "youtube",
        "url": "https://www.youtube.com/DeibyOd"
    },
    {
        "id": 6,
        "type": "blue",
        "title": "MIS ESCRITOS DIVERSOS",
        "content": {
            "text": "Algunas ideas y expresiones diversas."
        },
        "image": "blog",
        "url": "https://blog.deibyod.co"
    }
]